AUTHORS.rst
CONTRIBUTING.rst
HISTORY.rst
LICENSE
MANIFEST.in
README.rst
setup.cfg
setup.py
autoflpy/__init__.py
autoflpy/log_analysis.py
autoflpy.egg-info/PKG-INFO
autoflpy.egg-info/PKG-INFO-UOS-018283
autoflpy.egg-info/SOURCES.txt
autoflpy.egg-info/dependency_links.txt
autoflpy.egg-info/not-zip-safe
autoflpy.egg-info/top_level.txt
autoflpy/data/Data_sources.txt
autoflpy/data/Default_Template_(Full_Summary).ipynb
autoflpy/data/Input_File.json
autoflpy/data/Input_File_Template.json
autoflpy/data/Name_converter_list.txt
autoflpy/data/Your_logo_file_name_here.png
autoflpy/data/runways.csv
autoflpy/data/test_csv.CSV
autoflpy/data/test_log_to_xlsx.log
autoflpy/data/.ipynb_checkpoints/Default Template (Full Summary)-checkpoint.ipynb
autoflpy/data/.ipynb_checkpoints/Default_Template_(Full_Summary)-checkpoint-WINDOWS-VULKH01.ipynb
autoflpy/data/.ipynb_checkpoints/Default_Template_(Full_Summary)-checkpoint.ipynb
autoflpy/user_files/Data_sources.txt
autoflpy/user_files/Default_Template_(Full_Summary).ipynb
autoflpy/user_files/Input_File.json
autoflpy/user_files/Input_File_Template.json
autoflpy/user_files/METAR_storage/METAR_EGHE_20190110_20190110_15_15.txt
autoflpy/user_files/csv_flight_data/test_csv.CSV
autoflpy/user_files/excel_file_path/20190110_Flight01.pkl
autoflpy/user_files/excel_file_path/20190110_Flight01.xlsx
autoflpy/user_files/flight_logs_generated/Flight_report_20190110_Flight01.html
autoflpy/user_files/flight_logs_generated/Flight_report_20190110_Flight01.ipynb
autoflpy/user_files/flight_logs_generated/.ipynb_checkpoints/Flight_report_20190110_Flight01-checkpoint.ipynb
autoflpy/user_files/images/Your_logo_file_name_here.png
autoflpy/user_files/log_files/test_log_to_xlsx.log
autoflpy/util/__init__.py
autoflpy/util/flight_log_code.py
autoflpy/util/log_to_xlsx.py
autoflpy/util/metar_processing.py
autoflpy/util/name_generator.py
autoflpy/util/nearest_ICAO_finder.py
autoflpy/util/plotting.py
autoflpy/util/text_manipulation.py
autoflpy/util/analysis/__init__.py
autoflpy/util/analysis/environmental_data_processing.py
autoflpy/util/analysis/take_off_detection.py
autoflpy/util/testing/__init__.py
autoflpy/util/testing/check_str_in_content.py
docs/Makefile
