Metadata-Version: 1.2
Name: autoflpy
Version: 1.1.13
Summary: Automated flight log code
Home-page: https://github.com/AdrianWeishaeupl/AutoFLpy.git
Author: Adrian Benedikt Weishaeupl
Author-email: aw6g15@soton.ac.uk
License: UNKNOWN
Keywords: autoflpy
Platform: UNKNOWN
Classifier: Development Status :: 2 - Pre-Alpha
Classifier: Intended Audience :: Developers
Classifier: Natural Language :: English
Classifier: Programming Language :: Python :: 3
Classifier: Programming Language :: Python :: 3.5
Classifier: Programming Language :: Python :: 3.6
Classifier: Programming Language :: Python :: 3.7
Classifier: Programming Language :: Python :: 3.8
Requires-Python: !=3.0.*, !=3.1.*, !=3.2.*, !=3.3.*, !=3.4.*
